crypto_com_agent_client/__init__.py
crypto_com_agent_client/config/constants.py
crypto_com_agent_client/config/logging_config.py
crypto_com_agent_client/core/handlers/__init__.py
crypto_com_agent_client/core/handlers/interaction_handler.py
crypto_com_agent_client/core/model.py
crypto_com_agent_client/core/tools/__init__.py
crypto_com_agent_client/core/tools/block.py
crypto_com_agent_client/core/tools/contract.py
crypto_com_agent_client/core/tools/cronosid.py
crypto_com_agent_client/core/tools/defi.py
crypto_com_agent_client/core/tools/eip7702.py
crypto_com_agent_client/core/tools/exchange.py
crypto_com_agent_client/core/tools/token.py
crypto_com_agent_client/core/tools/tool_registry.py
crypto_com_agent_client/core/tools/transaction.py
crypto_com_agent_client/core/tools/wallet.py
crypto_com_agent_client/core/types/__init__.py
crypto_com_agent_client/core/types/defi.py
crypto_com_agent_client/core/workflows.py
crypto_com_agent_client/lib/__init__.py
crypto_com_agent_client/lib/client.py
crypto_com_agent_client/lib/enums/__init__.py
crypto_com_agent_client/lib/enums/cerebras_model_enum.py
crypto_com_agent_client/lib/enums/node_enum.py
crypto_com_agent_client/lib/enums/plugin_enum.py
crypto_com_agent_client/lib/enums/provider_enum.py
crypto_com_agent_client/lib/enums/role_enum.py
crypto_com_agent_client/lib/enums/workflow_enum.py
crypto_com_agent_client/lib/initializer.py
crypto_com_agent_client/lib/types/__init__.py
crypto_com_agent_client/lib/types/blockchain_config.py
crypto_com_agent_client/lib/types/chain_helper.py
crypto_com_agent_client/lib/types/erc20_ABI.json
crypto_com_agent_client/lib/types/factory_ABI.json
crypto_com_agent_client/lib/types/llm_config.py
crypto_com_agent_client/lib/types/memory_config.py
crypto_com_agent_client/lib/types/plugin_types.py
crypto_com_agent_client/lib/types/plugins_config.py
crypto_com_agent_client/lib/types/router_ABI.json
crypto_com_agent_client/lib/types/token_helper.py
crypto_com_agent_client/lib/types/wCRO_ABI.json
cryptocom_agent_client-1.3.6.dist-info/METADATA
cryptocom_agent_client-1.3.6.dist-info/WHEEL
cryptocom_agent_client-1.3.6.dist-info/entry_points.txt
cryptocom_agent_client-1.3.6.dist-info/RECORD
