Metadata-Version: 2.4
Name: cryptocom-agent-client
Version: 1.3.6
Summary: A Python client to interact with @cryptocom/agent
License: MIT
Keywords: blockchain,crypto.com,AI,tool,SDK
Author: Ric Arcifa
Author-email: ricardo.arcifa@crypto.com
Requires-Python: >=3.12,<4.0.0
Classifier: License :: OSI Approved :: MIT License
Classifier: Programming Language :: Python :: 3
Classifier: Programming Language :: Python :: 3.12
Classifier: Programming Language :: Python :: 3.13
Classifier: Programming Language :: Python :: 3.14
Requires-Dist: aiohappyeyeballs (==2.6.1)
Requires-Dist: aiohttp (==3.11.16)
Requires-Dist: anthropic (==0.49.0)
Requires-Dist: botocore (>=1.34.0,<2.0.0)
Requires-Dist: crypto-com-developer-platform-client (==1.1.1)
Requires-Dist: cryptocom-agent-plugin-discord (>=1.0.1,<2.0.0)
Requires-Dist: cryptocom-agent-plugin-sqlite (>=1.0.3,<2.0.0)
Requires-Dist: cryptocom-agent-plugin-telegram (>=1.1.5,<2.0.0)
Requires-Dist: discord.py (==2.5.2)
Requires-Dist: eth-account (==0.13.6)
Requires-Dist: eth-utils (==5.3.0)
Requires-Dist: fireworks-ai (==0.15.12)
Requires-Dist: google-api-python-client (==2.167.0)
Requires-Dist: google-auth (==2.39.0)
Requires-Dist: google-cloud-aiplatform (==1.93.0)
Requires-Dist: google-cloud-bigquery (==3.34.0)
Requires-Dist: google-generativeai (==0.8.4)
Requires-Dist: groq (==0.24.0)
Requires-Dist: httpx (==0.28.1)
Requires-Dist: langchain (==0.3.23)
Requires-Dist: langchain-anthropic (>=0.3.1,<0.4.0)
Requires-Dist: langchain-aws (>=0.2.0)
Requires-Dist: langchain-cerebras (>=0.7.0,<0.8.0) ; python_version == "3.12"
Requires-Dist: langchain-core (==0.3.81)
Requires-Dist: langchain-fireworks (>=0.2.6,<0.3.0)
Requires-Dist: langchain-google-genai (>=2.0.8,<3.0.0)
Requires-Dist: langchain-google-vertexai (>=2.0.24,<3.0.0)
Requires-Dist: langchain-groq (>=0.3.2,<0.4.0)
Requires-Dist: langchain-mistralai (>=0.2.4,<0.3.0)
Requires-Dist: langchain-openai (>=0.3.12,<0.4.0)
Requires-Dist: langchain-xai (>=0.2.3,<0.3.0)
Requires-Dist: langfuse (==2.57.5)
Requires-Dist: langgraph (==0.2.61)
Requires-Dist: numpy (>=1.26.0,<2.0.0)
Requires-Dist: openai (==1.74.0)
Requires-Dist: pydantic (==2.10.4)
Requires-Dist: python-dotenv (==1.0.1)
Requires-Dist: requests (==2.32.4)
Requires-Dist: web3 (==7.10.0)
Project-URL: Documentation, https://github.com/crypto-com/agent-client-py#readme
Project-URL: Homepage, https://github.com/crypto-com/agent-client-py
Project-URL: Repository, https://github.com/crypto-com/agent-client-py
